{
    "labels": {
        "NameOrNumber": "姓名或编号",
        "action": "动作",
        "emailList": "Email List",
        "emailText": "Please separate multiple recipients with semi-colons",
        "enterSomeVaule": "请输入有效搜索条件，以继续搜索。",
        "generateReport": "Generate Report",
        "ggp": "Great Grand Parent",
        "ggpNumber": "GGP 号码:",
        "gp": "Grand Parent",
        "hierarchyReviewHeading": "Hierarchy Review",
        "hierarchyReviewText": "To get the results please provide a search type,input list and email list.",
        "inputList": "Input List",
        "lastName": "姓",
        "logDate": "日志日期",
        "masterDataHeading": "主数据日志",
        "masterDataLogText": "以下项目可能需要收件人。要定位特定项目，您可以通过出售至、姓名\/编号、主要组名称\/编号或联系人姓氏进行搜索。",
        "masterGroup": "主要组",
        "noRecordsFound": "未找到与您的帐户簿相关的记录。",
        "note": "Note",
        "reportingParentLabel": "报告父结点",
        "rp": "Reporting Parent",
        "searchButton": "搜索",
        "searchResultsMDL": "搜索结果",
        "select": "Select",
        "selectType": "Select Type",
        "soldto": "Soldto",
        "update": "更新",
        "updateHierarchysubtitle": "更新网络组的等级, 提供GGP和网络组的号码 :",
        "updateHierarchytitle": "更新网络组的等级",
        "webGrpSoldTo": "出售至",
        "webGrpUser": "顾客姓名",
        "webgroupNumber": "网络组号码 :"
    }
}