{
    "labels": {
        "enable_live_chat": "Live-Chat aktivieren",
        "ewr_fees_in_cart": "EWR-Gebühren im Warenkorb anzeigen",
        "override_payment_options": "Zahlungsoptionen überschreiben",
        "enable_b2b_exit": "B2b Exit aktivieren",
        "suppress_sell_req": "Verkaufsanforderungen unterdrücken",
        "suppress_lab_config_notes_field": "Feld „Labor Config Notes“ unterdrücken",
        "web_reference_po_default": "Verwenden Sie die Web-Referenznummer als Vorgabe für die Bestellung",
        "opt_out_of_post_purchase_survey_popup": "",
        "enable_hosted_licensing_dashboard_spla": "SPLA",
        "enable_buy": "Menü für „Produkte“ einschalten",
        "unspsc_code": "UNSPSC-Code",
        "Opt_out_of_product_review_emails": "Opt out of product review emails",
        "disable_stock_and_price_display": "Bestands- und Preisanzeige deaktivieren",
        "hide_po_fields_checkout": "Auftragsfelder beim Bezahlen ausblenden",
        "allow_upload": "Dateihochladen beim Bezahlen zulassen – Erlauben Sie allen Kontakten innerhalb der Web-Gruppe, optional eine Datei hochzuladen, die 5 MB oder weniger groß und vom Typ ist: zip, csv, txt, doc, docx, msg, odt, rtf, wpd, wps, pps, ppt, pptx, mpp, xlsb, xls, xlr, xlsx, bmp, pdf, jpeg, gif, png. Das Dokument kann über die Auftragshistorie heruntergeladen werden.",
        "allow_logout_redirect": "Abmeldeumleitung zulassen",
        "apply_for_lease": "„Für Lease anwenden“ aktivieren",
        "insight_news": "Insight News",
        "frt_estimator": "Schätzung der Frachtkosten im Warenkorb",
        "business_rel_sort_by": "Nach Bestsellern sortieren",
        "allow_unlimited_spla_ordering": "Unbegrenzte SPLA-Bestellungen zulassen",
        "enable_generic_order_history": "Generische Auftragshistorie aktivieren",
        "greater_access_shipping_address": "Zugriff auf alle Versandadressen zulassen",
        "allow_shipping_complete": "„Versand vollständig“ zulassen",
        "enable_hosted_licensing_dashboard": "Hosted Licensing Dashboard aktivieren",
        "stars_notify_customer": "STARS – Kunde@benachrichtigen",
        "enable_cloud_buying": "Cloud-Kauf aktivieren",
        "display_alt_po_release_label_checkout": "Etikett für alternative Auftragsfreigabe beim Bezahlen anzeigen",
        "stars_notify_insight": "STARS – Notify@insight.com",
        "display_adnl_notes_tran_process": "Zusätzliche Notizen während des Transaktionsprozesses anzeigen",
        "standard_unspsc_code": "Standard-UNSPSC-Code",
        "display_inv_notes_tran_process": "Zusätzliche Rechnungsnotizen während des Transaktionsprozesses anzeigen",
        "hostedLicensing": "Gehostete Lizenzierung:",
        "suppress_po_release_checkout": "Auftragsfreigabenummer unterdrücken",
        "allow_unlimited_citrix_ordering": "Unbegrenzte Citrix Bestellung zulassen",
        "enable_solve": "„Menü für Lösungen“ freigeben",
        "enable_manage": "Menü für „Verbinden“ einschalten",
        "display_sap_quantity": "Insight Lagerinventar anzeigen",
        "webgroup_marketing_includes": "„Marketing umfasst“ aktivieren",
        "allow_convert_quote_billingplans": "Konvertierung des Angebot bei Fakturierungsplänen zulassen",
        "allow_report_delivery_to_ftp": "Berichtsübermittlung an FTP zulassen",
        "list_price": "Listenpreis anzeigen",
        "suppress_shipping_estimate_in_cart": "Suppress Shipping Estimate in Cart",
        "req_po_num_at_checkout": "Auftragsnummer beim Bezahlen erforderlich",
        "allow_file_upload": "Hochladen der Datei beim Bezahlen zulassen",
        "enable_hosted_licensing_dashboard_citrix": "CITRIX",
        "suppress_shared_user_fields": "Felder für geteilte Benutzer unterdrücken",
        "suppress_country_usage": "Einsatzland unterdrücken",
        "enable_learn": "Menü für „Inhalt & Ressourcen“ aktivieren",
        "standardized_login": "Fähigkeit zum Ändern des Benutzernamens deaktivieren"
    }
}