{
    "labels": {
        "CurrentMyCompany": "",
        "EditMyCompanyPage": "Editar la página de mi empresa",
        "MyCompanyTitle": "Gestionar grupo web: Mi empresa",
        "alert": "Alertar",
        "b": "( b) ",
        "by": "Por",
        "cancelButton": "Cancelar",
        "changesToApprove": "Hay cambios a la espera de aprobación ",
        "ckeditorOldInstance": "¡La instancia de CKEditor ya existe! No se ha podido eliminar",
        "companyPageDisabled": "Página de la empresa desactivada",
        "companyPageEnabled": "Página de la empresa activada",
        "completeMessage": "Insight proporciona soluciones de TI completas, incluyendo ventas, servicio y distribución de hardware informático, software y periféricos de fabricantes líderes, así como una gama completa de servicios de gestión de tecnología. Los equipos de gestión de cuentas dedicados proporcionan el más alto nivel de servicio personalizado y satisfacción del cliente a empresas de todo el país. Somos su socio de servicios tecnológicos de valor añadido en un solo paso, y contamos con una vasta selección de productos, excelentes precios y un servicio de entrega rápida de miles de productos informáticos para su negocio.",
        "copyButton": "copia",
        "copySuccess": "Copiado correctamente. ",
        "copyToAnother": "Copiar página actual a otro cliente:",
        "createDate": "Crear fecha",
        "currentMyCompanyPage": "Mi empresa actual ",
        "currentTestPage": "Página actual de mi empresa",
        "customClientSupportNumber": "Número de teléfono de soporte personalizado del cliente:",
        "customContent": "Contenido personalizado:",
        "deleteButton": "ELIMINAR",
        "displayOnWeb": "Mostrar esto en la web",
        "editButton": "editar",
        "editWelcomePage": "Editar la página de mi empresa",
        "endDateStartDate": "La fecha de finalización no puede ser anterior a la fecha de inicio",
        "fourteen": "14",
        "image": "Imagen",
        "imageSelect": "Seleccionar imagen",
        "imageType": "(gif o jpg):",
        "insightNews": "Noticias de Insight",
        "insightNewsDisplay": "Las noticias de Insight se mostrarán aquí.",
        "insightNewsExtra": "Ver Noticias de Insight (información de la cuenta relacionada con la web, como interrupciones y mejoras).",
        "insightSite": "www.insight.com\/",
        "invalidCustomerNumber": "Introduzca un número de cliente válido",
        "lastUpdate": "Última actualización",
        "myCompanyPageOFF": "Desactivado",
        "myCompanyPageON": "En",
        "myCompanyPagePreview": "Vista previa de la página de mi empresa",
        "noDefaultsAvailable": "No se ha encontrado ninguna página personalizada para este cliente, se usarán valores predeterminados.",
        "previewChanges": "Vista previa de los cambios",
        "previewPage": "Vista previa de la página",
        "publishButton": "Publicar",
        "requestApproval": "Solicitar aprobación",
        "runReport": "N.º de nivel terciario (GGP)\/comprador único",
        "sixteen": "16",
        "success": "Ha funcionado",
        "ten": "10.",
        "twelve": "12.",
        "vanityUrl": "Dirección URL personalizada:",
        "webGroupNumber": "Número de grupo web:",
        "welcomeHeadline": "Encabezado de bienvenida:",
        "welcomeImage": "Imagen de bienvenida",
        "welcomeMessage": "Bienvenido\/a, [ nombre de usuario ]: ",
        "welcomePagePreview": "Vista previa de la página de bienvenida",
        "welcomePageTitle": "Gestionar el grupo web: Mi página de empresa",
        "welcomeTestAccountChange": "Cuenta de prueba de bienvenida – Cambiar"
    }
}