{
    "labels": {
        "AccountLevel": "Account Level",
        "AddAdditionalEmail": "+Add additional email",
        "AddHocColumn": "AddHoc Column",
        "AddHocDateBy": "AddHoc Date By",
        "AddHocOrderBy": "AddHoc Order By",
        "Cancel": "Cancel",
        "Close": "Close",
        "Comma": "Comma",
        "CreatedBy": "Created By",
        "CustomName": "Custom Name:",
        "CustomerNumber": "Customer Number",
        "Delete": "Delete",
        "Delimiters": "Delimiters:",
        "Edit": "Edit",
        "Email": "Email",
        "EndDate": "End Date",
        "Other": "Other:",
        "ReportName": "Report Name",
        "Run": "Run",
        "Save": "Save",
        "Scheduled": "Scheduled",
        "Semicolon": "Semicolon",
        "Space": "Space",
        "StartDate": "Start Date",
        "Tab": "Tab",
        "TrackingNumber": "Tracking Number",
        "UserName": "User Name",
        "accounts": "Accounts",
        "accumulateResults": "Accumulate Results",
        "allMyAccount": "ALL My Accounts",
        "created_by": "Created By",
        "currency": "Currency",
        "customListOfAcc": "Custom List of Selected Account",
        "deliveryDateFormat": "Date Format",
        "deliveryMethod": "Delivery Method",
        "end_date": "End Date",
        "format": "Format",
        "ftpLocation": "FTP Location",
        "insight_public_sector_data": "Insight Public Sector Data",
        "interval1": "Interval",
        "invalidEmailAddressError": "At least one email entered is invalid.",
        "manufacturerFilter": "Manufacturer Filter",
        "missingEmailAddressError": "At least one email address is required.",
        "partner_data": "Partner Data",
        "pleaseWaitLabel": "Please wait..",
        "posted_reports_blurb": "Access reports that were conveniently stored for you.",
        "posted_reports_title": "Posted Reports",
        "pr_header_created_by": "Created By",
        "pr_header_custom_name": "Custom Report Name",
        "pr_header_format": "Format",
        "pr_header_interval": "Interval",
        "pr_header_options": "Options",
        "pr_header_report_name": "Report name",
        "pr_header_report_type": "Report Type",
        "pr_header_run_date": "Run Date",
        "renew": "Renew",
        "report_name": "Report Name",
        "report_templates_blurb": "No more re-entering reporting criteria! Save your report settings as a template and run a report quickly using the Template. You can also edit and delete.",
        "report_templates_title": "Report Templates",
        "reportingGrandGrandParent": "Great Grand Parent",
        "reportingGrandParent": "Reporting Grand Parent",
        "reportingParent": "Reporting Parent",
        "reporting_management": "Reporting Management",
        "reports": "Reports",
        "rt_header_created_by": "Created By",
        "rt_header_last_run_date": "Last Run Date",
        "rt_header_options": "Options",
        "rt_header_report_format": "Format",
        "rt_header_report_name": "Report Name",
        "rt_header_report_type": "Report Type",
        "rt_header_template_name": "Template Name",
        "run_new_report": "New Report",
        "scheduled_reports_blurb": "Easily view the schedule of your re-occurring reports. You can also quickly run the report or delete the schedule.",
        "scheduled_reports_title": "Scheduled Reports",
        "selectedOpsCenter": "Operations Centers",
        "selectedRegion": "Region",
        "selected_product_category": "Selected Product Category",
        "selected_product_sub_category": "Selected Product Subcategory",
        "selected_product_types": "Selected Product Types",
        "serviceFailedError": "service failed",
        "smartTracker": "SmartTracker",
        "sr_header_created_by": "Created By",
        "sr_header_exp_date": "Exp. Date",
        "sr_header_format": "Format",
        "sr_header_interval": "Interval",
        "sr_header_options": "Options",
        "sr_header_report_name": "Report Name",
        "sr_header_tracking_number": "Tracking Number",
        "start_date": "Start Date",
        "tracking_number": "Tracking Number",
        "view": "View",
        "viewDef": "View Report Definition"
    }
}