{
    "labels": {
        "ReportsRequisitionSearch": "申请状态报告",
        "reportRequestorGroups": "申请人组",
        "reportReplacementType": "替代类型",
        "appPayementMethod": "支付方式",
        "rulesSmartTrackers": "智能跟踪程序",
        "appSHipToAddress": "发货至地址",
        "noRecordsFound": "未找到记录。",
        "ApprovedReq": "批准的请求",
        "GroupRulesHeading": "申请人组规则报告",
        "ReportsTo": "至",
        "requestorCancellationSettings": "允许申请人取消申请",
        "rulesShowUser": "显示用户",
        "rulesSettings": "设置",
        "lessThanYear": "范围需少于一年!",
        "noApprovalPath": "无审批路径",
        "bothApproverAndRequestor": "审批人和申请人",
        "rulesTotalNumSetting": "设置总数",
        "lineLevel": "行等级",
        "rulesPartial": "部分",
        "smartTracker": "只能追踪器",
        "reportSmartTrackName": "智能跟踪程序名称",
        "nonStandard": "非标准",
        "rulesSndRemainderMails": "发送提醒电子邮件",
        "OpenReq": "开放申请",
        "noHeaderLevelSTs": "无页眉等级的智能跟踪程序",
        "requestorOnly": "仅申请人",
        "DeniedReq": "拒绝的申请",
        "editCart": "修改购物车",
        "reportUserName": "用户名",
        "reportRequestorGroup": "申请人组",
        "reportShow": "显示",
        "ReportsRequestedDate": "申请日期",
        "approvalPath": "批准路径",
        "reportApproveGroupName": "审批组名称",
        "reportRequisitionStatus": "状态",
        "reportShipDate": "发货日期",
        "min": "最小",
        "ReportsFrom": "自",
        "rulesExact": "准确",
        "RulesGroupname": "组名称：",
        "appBillToAddress": "开票至地址",
        "max": "最大",
        "reportsOOF": "审批人外部报告",
        "rulesCartType": "购物车类型",
        "reportEndDate": "结束日期",
        "requestorGroupName": "申请人组名称",
        "reportStartDate": "起始日期",
        "selectOne": "选择一项",
        "ApprovedAndDeniedReq": "已审批\/拒绝的申请",
        "headerLevel": "页眉等级",
        "noShippingOptionsSelected": "未选择发货选项",
        "ReportsFilterStatus": "按状态筛选",
        "allowApproverToEdit": "允许审批人编辑",
        "reportSmartTracker": "智能跟踪程序",
        "ApprovalManagementMainHeading": "审批管理",
        "reportAppPathName": "审批路径名",
        "totalNumberOfApprovers": "审批人总数",
        "first": "第一个",
        "noPaymentOptionsSelected": "未选择支付选项",
        "All": "全部",
        "standard": "标准",
        "CancelledReq": "取消的请求",
        "rulesEvaluateOrder": "规则评估顺序",
        "ReqUnderReview": "",
        "rulesDefaultAppPath": "默认审批路径",
        "reportOrderDate": "订单日期",
        "rules": "规则",
        "rulesCustomeCheckout": "自定义结账值：",
        "zero": "0",
        "approverOnly": "仅审批人",
        "noSmartTracker": "无智能跟踪器",
        "rulesSearch": "搜索",
        "lastNameSoloToOrNumber": "姓氏或帐号",
        "ReportsFilterByDate": "按申请日期筛选",
        "ReportsManagementLink": "审批管理报告",
        "Order": "订单",
        "reportAprrover": "审批人",
        "reportsSmartTrack": "申请人组 SmartTracker 报告",
        "noLineLevelSTs": "无行等级的智能跟踪程序",
        "reportRequestor": "申请人",
        "rulesPayementOptions": "支付选项",
        "rulesDollarAmount": "金额",
        "last": "最后一个",
        "reportRequestrGroupName": "申请人组名称",
        "noRules": "无规则",
        "reportStatus": "申请状态报告",
        "customField": "自定义字段",
        "users": "用户",
        "viewAll": "查看全部",
        "never": "从不",
        "reportRules": "申请人组规则报告",
        "allActions": "所有动作",
        "seeAllReports": "查看所有报告",
        "final": "最终",
        "rulesUpdateEmails": "发送更新电子邮件",
        "reportDays": "审批天数<br\/>",
        "reportsPathApp": "审批路径报告",
        "rulesShippingOptions": "发货选项",
        "appPoNumber": "PO 编号",
        "next": "下一个",
        "reportsGroupUser": "申请人组用户",
        "appShipCarrier": "发货承运人",
        "rulesSearchRequestorName": "申请人组名称",
        "reportResultsPerPage": "每页结果数",
        "rulesShowRules": "显示规则",
        "reportReplaceApprover": "替代审批人",
        "previous": "上一个",
        "reportRequiOrder": "申请单号",
        "any": "任意",
        "rulesCheckoutOptions": "结账选项",
        "currencyRange": "货币范围",
        "reportApproverOut": "审批人外部",
        "noUsers": "无用户",
        "searchRequestorGroup": "搜索特定申请人组"
    }
}