{
    "labels": {
        "InsightOutgoingSerial": "Insight utgående serienr",
        "Notify": "Meddela",
        "Customer": "Kund",
        "WestVirginia": "West Virginia",
        "pararef": "Om du begär en hel enhet ska du inte fylla i informationen om defekta delar nedan.",
        "RepairDetailSummary": "Översikt över reparationsdetaljer",
        "ImageType": "Bildtyp",
        "TotalCost": "Total kostnad",
        "SeedProblem": "Seed-problem",
        "DateShipped": "Leveransdatum",
        "LastModifiedby": "Senast ändrad av",
        "DateBackToStock": "Datum tillbaka till lager",
        "RepairInfo": "Reparationsinformation",
        "CallCenterRepDetails": "Information om callcenter-representanten ",
        "EditAllDropboxContents": "Redigera allt Dropbox-innehåll",
        "California": "Kalifornien",
        "AdditionalPartDetails": "Ytterligare artikelinformation",
        "IDsWaitingForRANumber": "ID:n som väntar på R.A.-nummer",
        "ChooseSearchArea": "Välj sökområde",
        "RequestedItemEdit": "Redigera begärd artikel",
        "Exchange": "Exchange",
        "Mississippi": "Mississippi",
        "ProjMngmntDetails": "Omplaceringsinformation om projektledning",
        "Activate": "Aktivera",
        "StandAlone": "Fristående",
        "Maryland": "Maryland",
        "CustomerDefinedData": "Kunddefinierade uppgifter",
        "Link": "Länk",
        "EquipPartSerial": "Utrustningens eller artikelns serienr",
        "emailAlertto": "e-postvarning till",
        "CustomerEdit": "Kundredigering",
        "Oklahoma": "Oklahoma",
        "DeploymentSummary": "Distributionsöversikt",
        "Arkansas": "Arkansas",
        "AdministrativeMaintenance": "Administrativt underhåll",
        "search": "Sök",
        "NewYork": "New York",
        "InsightDepoetails": "Information om Insight Depot",
        "tesrdext": "test rd text",
        "DefaultShiToInformation": "Förvald leveransinformation",
        "Nevada": "Nevada",
        "repairInfoRec": "Din reparationsinformation har registrerats.",
        "EquipmentRepairNeeds": "Reparationsbehov för utrustning",
        "ShipToName": "Mottagarnamn",
        "PMComments": "PM-kommentarer",
        "Reporting": "Rapportering",
        "IncomingShippingTracking": "Spårning av inkommande leverans",
        "DeploymentRequestrecorded": "Din distributionsbegäran har registrerats.",
        "Michigan": "Michigan",
        "days": "dagar",
        "Submit": "Skicka",
        "Phone Number": "Telefonnummer",
        "ExpressExchangeNotrecorded": "Din Express Exchange har INTE registrerats.",
        "InventorySeedEntry": "Seed-lagerinmatning",
        "ADD": "Lägg till",
        "EndUserDetails": "Slutanvändaruppgifter",
        "ExpressExchangerecorded": "Din Express Exchange har registrerats.",
        "Email": "E-postadress",
        "FailedNoParts": "Skadade\/inga artiklar",
        "DateToStock": "Datum till lager",
        "Wyoming": "Wyoming",
        "FailedSeedEntry": "Misslyckad seed-inmatning",
        "ExpressExchangeID": "Express Exchange-ID",
        "Deployment": "Implementering",
        "IdentifyitemoldSerialNos: ": "Identifiera artiklar och gamla och nya resurstaggar och serienummer: ",
        "SelectUnitShip": "Välj enhet att skicka",
        "RepairDetails": "Reparationsinformation",
        "IncomingTracking": "Spårning av inkommande",
        "DisposalDate": "Kasseringsdatum",
        "entereditrepairdetails": "Ange\/redigera reparationsinformation",
        "EnterRequest": "Ange begäran",
        "DefectivePartNameModel": "Defekt artikels namn och modell",
        "ReceivedbuNotEvaluated": "Mottagen men inte utvärderad",
        "EquipmentSerial": "Utrustningens serienr",
        "Test": "Test",
        "Insight": "Insight",
        "warning": "Varning!",
        "ChooseOutboundUnit": "Välj utgående enhet",
        "EnterExpressExchangeRequest": "Ange en annan Express Exchange-begäran",
        "youmayenterunitsin": "Du kan ange enheter i",
        "DefectiveEquipParModel": "Defekt utrustnings eller artikels modell",
        "NorthernMarianaIslands": "Nordmarianerna",
        "Failed": "Misslyckade",
        "For": "för",
        "CustomerTicket": "Kundärende",
        "AccessLevel": "Åtkomstnivå",
        "SerialNumber": "Serienummer",
        "State": "Stat",
        "RepairStatus": "Reparationsstatus",
        "EmployeeID": "Anställnings-ID",
        "EmployeeName": "Medarbetarens namn",
        "Vermont": "Vermont",
        "AllCustomers": "Alla kunder",
        "ScreensavePassword": "Lösenord för skärmsläckare",
        "back": "Tillbaka",
        "Alabama": "Alabama",
        "Tonarrowdownyoursearch": "Om du vill precisera din sökning kan du även ange sökvillkor i andra fält som anges nedan.",
        "DecisionMadeBy": "Beslut fattat av",
        "RepairDetailLink": "Länk till reparationsinformation",
        "OutgoingSAPOrder": "Utgående SAP-beställning",
        "EquipmentAssetTag": "Utrustningens resurstagg",
        "AcceptedDate": "Accepterat datum",
        "SelectOption": "Välj alternativ",
        "Colorado": "Colorado",
        "BotUSInternational": "Både USA och internationellt",
        "passed": "Godkänd",
        "CustomerName": "Kundens namn",
        "ShipmenMethod": "Leveransmetod",
        "EquipParModel": "Utrustningens eller artikelns modell",
        "ExpressExchangeIDTitle": "Express Exchange-ID",
        "International": "Internationellt",
        "ReturntoMenu": "Gå tillbaka till menyn",
        "Minnesota": "Minnesota",
        "Admin": "Administratör",
        "TestDepotDefinedData": "Testdepå-definierade data",
        "CreateRepairDetail": "Skapa reparationsinformation",
        "White": "Vit",
        "fromlabel": "Från",
        "EndUserFullName": "Slutanvändarens fullständiga namn",
        "PartDescription": "Artikelbeskrivning",
        "Ohio": "Ohio",
        "EquipmentWaitingForDepotShipment": "Utrustning som väntar på depåleverans",
        "Address": "Adress",
        "Remove": "Ta bort",
        "FieldTitle": "Fälttitel",
        "DateTime": "Datum och tid",
        "DateScanneentoSymbol": "Datum då skannern skickades till Symbol",
        "LastModified": "Senast ändrad",
        "ItemsYetToBeReceivedADepot": "Artiklar som ännu inte har tagits emot i depån",
        "ChooseUserforAdd": "",
        "PreFilledInformation": "Information ifylld i förväg",
        "RepairInfoProjec": "Reparationsinformationens projektdetaljer",
        "ie": "dvs.",
        "InsightRA": "Insight R.A.",
        "NotusedinDeployment": "Används inte i sökningar efter distributionsbegäran",
        "RelatedExpressExchangeID": "Relaterat Express Exchange-ID",
        "Montana": "Montana",
        "StateRegion": "Delstat\/region",
        "ChooseUserforEdit": "Välj användare för redigering",
        "Kentucky": "Kentucky",
        "DescribeProblem": "Beskriv problemet",
        "Pleasehityour": "Tryck på din",
        "GoBACKtofixthisoversight": "Gå TILLBAKA för att rätta detta misstag.",
        "Delaware": "Delaware",
        "Florida": "Florida",
        "AddUser": "",
        "Canada": "Kanada",
        "EndUserName": "Slutanvändarens namn",
        "EnteranotherDeploymentRequest": "Ange en annan distributionsbegäran",
        "LoginProfileID": "Inloggningsprofil-ID",
        "AmericanSamoa": "Amerikanska Samoa",
        "Virginia": "Virginia",
        "Canuseredit": "Kan användaren redigera denna adress",
        "EditDepotUserDefinedFields": "Redigera depåanvändardefinierade fält",
        "FixedField": "Fast fält",
        "EditCustomerUserDefinedFields": "Redigera kundanvändardefinierade fält",
        "ExpressExchangeSummary": "Express Exchange-översikt",
        "enUsEmp": "Slutanvändarens anställnings-ID ",
        "ifapplicable": "om tillämpligt",
        "CannotRepair": "Kan inte reparera",
        "ReturnTracking": "Returspårning",
        "MiddleEast": "Mellanöstern",
        "Menu": "Meny",
        "ClearFields": "Rensa fält",
        "ChooseType": "Välj typ",
        "DepotSideUserDefinedFieldsEdit": "Redigera depåanvändardefinierade fält",
        "ProjMngNotes": "Projektledningens anteckningar",
        "Allowed": "Tillåtet",
        "NorthCarolina": "North Carolina",
        "Pacific": "Stillahavsområdet",
        "OriginatedDateTime": "Ursprungligt datum och tid",
        "DepotDefinedData": "Depådefinierade data",
        "ReturnToSearchcriteria": "Gå tillbaka till sökvillkoren",
        "report": "rapport",
        "RequestedShipDate": "Begärt leveransdatum",
        "Palau": "Palau",
        "complete": "Slutförda",
        "ProjMngmnedispositionDetails": "Omplaceringsinformation om projektledning",
        "Unit": "Enhet",
        "SearchArchivedRecords": "Sök arkiverade poster",
        "ExpressExchangeProjectDetails": "Information om Express Exchange-projekt",
        "DefectiveEquipmentModelEdit": "Redigera defekt utrustningsmodell",
        "Guam": "Guam",
        "Reset": "Återställ",
        "UserDefinedFieldsDepot": "Användardefinierade fält – Insight",
        "Accept": "Acceptera",
        "UserCanEdit": "Användaren kan redigera",
        "Europe": "Europa",
        "City": "Ort",
        "Successful": "Slutfört",
        "vieweditrepairdetails": "Visa\/redigera reparationsinformation",
        "OutboundSerial": "Utgående serienr",
        "openEntryField": "Öppet inmatningsfält",
        "na": "ej tillämpligt",
        "NoteAdmin": "Välj ett företag i den nedrullningsbara listrutan och klicka på Fortsätt för att fortsätta.",
        "YouarotauthorizedviewExpressExchangeRequest": "Du har inte behörighet att visa denna Express Exchange-begäran",
        "AdminSearchUtility": "Administratörens sökverktyg",
        "EditThisUser": "Redigera denna användare",
        "ChoosCustomerfor": "Välj kund för",
        "NO": "Nej",
        "no": "Nej",
        "Maine": "Maine",
        "Tennessee": "Tennessee",
        "emailAlertCustomer": "e-postvarning till kund",
        "noOutboundUnits": "Det finns inga utgående enheter som är klara för distribution.",
        "ContractID": "Avtals-ID",
        "REQUIREDFIELD": "OBLIGATORISKT FÄLT",
        "RejectedAndEquipmentStillAtDepot": "Avvisad och utrustning fortfarande i depån",
        "DateRange": "Datumintervall",
        "linesrecorded": "registrerade rader",
        "Phone": "Telefon",
        "DefectivePartModelEdit": "Redigera defekt artikels modell",
        "EndUserEditor": "Redigerare för slutanvändare",
        "UserUpdateResults": "Resultat av användaruppdatering",
        "Comment": "Kommentar",
        "chooseRequestedItem": "Välj begärd artikel",
        "comments": "Kommentarer",
        "SiteCode": "Platskod",
        "CurrentRequestetemDropboxContents": "Dropbox-innehåll för aktuellt begärd artikel",
        "DefectiveEquipmentDetails": "Information om defekt utrustning",
        "ProductCategoryModelNumber": "Produktkategori\/modellnummer",
        "DepotAdministrator": "Depåadministratör",
        "OutboundParName": "Namn på utgående artikel",
        "DistrictOfColumbia": "District of Columbia",
        "Depot": "Depå",
        "WaitingToBeRepaired": "Väntar på att repareras",
        "Archive": "Arkivera",
        "PartNumber": "Artikelnummer",
        "Indiana": "Indiana",
        "DateEntered": "Angivet datum",
        "RejectionDate": "Avslagsdatum",
        "SeedInventoryEntry": "Seed-lagerinmatning",
        "ReplacementNote": "Anteckning om utbyte",
        "DateReceived": "Mottagningsdatum",
        "Edit": "Uppdatera",
        "RANumber": "R.A.-nummer",
        "ItemsYetTBeShippeByDepot": "Artiklar som ännu inte har skickats av depån",
        "OutboundModel": "Utgående modell",
        "Reject": "Neka",
        "printerOkidata": "SKRIVARE Okidata 320 Turbo",
        "ForTest": "För test",
        "downloadToExcel": "Hämta till Excel",
        "notReqd": "Krävs inte",
        "ERROR": "Fel",
        "Repair": "Reparation",
        "DeploymentProjecetails": "Information om distributionsprojekt",
        "Background": "Bakgrund",
        "Africa": "Afrika",
        "DefectivePartDetails": "Information om defekt artikel",
        "DefectivEquipPartAsset": "Resurstagg för defekt utrustning\/artikel",
        "NotetoDepot": "Meddelande till depån",
        "TestCustomer": "Testkund",
        "Americas(exceptCanada)": "Amerika (utom Kanada)",
        "Details": "Detaljer",
        "Illinois": "Illinois",
        "Georgia": "Georgia",
        "Tempe": "Tempe",
        "Idaho": "Idaho",
        "ReadyFoDeployment": "Klar för distribution",
        "SouthCarolina": "South Carolina",
        "EditUser": "Redigera användare",
        "SubTotal": "Delsumma",
        "pulldown": "rullgardinsmeny",
        "Washington": "Washington",
        "InternationaIndicator": "Internationell indikator",
        "IncomingSerial": "Inkommande serienr",
        "Parts": "Artiklar",
        "Missouri": "Missouri",
        "ArmedForcesDestinations": "Armed Forces-destinationer",
        "SLAMet": "SLA uppnått",
        "Wisconsin": "Wisconsin",
        "ReturntoAdminMenu": "Gå tillbaka till administrationsmenyn",
        "Express": "Express",
        "CurrentDefectivePartModeDropbox": "Dropbox-innehåll för aktuellt defekt artikels modell",
        "Keysdorespondkeyboard": "Tangenterna reagerar inte. Platsen har även rengjort tangentbordet",
        "ReturnTo": "Gå tillbaka till",
        "FirstName": "Förnamn",
        "Hawaii": "Hawaii",
        "FederatedStatesofMicronesia": "Mikronesien",
        "Decisionby": "Beslut av",
        "Decision": "Beslut",
        "Spare": "Reserv",
        "PhoneNumber": "Telefonnummer",
        "buttonsubmitheform": "och skicka formuläret igen",
        "PriceEach": "Pris per st.",
        "IFREPLACEDDETAILS ": "OM BYTE SKA DU ANGE DELL-UTBYTESDETALJER ",
        "noteEmail": "Ange kommaåtskilda listor med e-postadresser",
        "SelectOne": "Markera ett alternativ",
        "EquipmenEvaluation": "Utvärdering av utrustning",
        "PleashoosetheCustomer": "Välj kunden (eller alla företag) och databasen för att söka",
        "tolabel": "Till",
        "RequestedItem": "Begärd artikel",
        "FieldOptions": "Fältalternativ",
        "BaseRANumber": "RA-basnummer",
        "EquipmentType": "Utrustningstyp",
        "EditThisCustomer": "Redigera denna kund",
        "Name": "Namn",
        "BackToSite": "Tillbaka till platsen",
        "DataEntry": "Datainmatning",
        "RepairedSpareDate": "Reparerad reservdels datum",
        "incomplete": "Ofullständig",
        "StoreNumber": "Butiksnummer",
        "DatShippedOut": "Avsändningsdatum",
        "DepotShippedDetails": "Information om avsänt från depån",
        "ExpressExchangeRequest": "Express Exchange-begäran",
        "fromanExpressExchange": "från en Express Exchange",
        "UpdateRequest": "Uppdateringsbegäran",
        "USOnly": "Endast USA",
        "Kansas": "Kansas",
        "EvaluationDate": "Värderingsdatum",
        "Pennsylvania": "Pennsylvania",
        "ReceivedDate": "Mottagningsdatum",
        "Iowa": "Iowa",
        "Texas": "Texas",
        "NewMexico": "New Mexico",
        "ProductCategory": "Produktkategori",
        "Enter": "Ange",
        "Region": "Region",
        "DeploymentRequest": "Distributionsbegäran",
        "EditDropDownLists": "Redigera nedrullningsbara listrutor",
        "LastName": "Efternamn",
        "SouthDakota": "South Dakota",
        "TrackingNumber": "Spårningsnummer",
        "Yes": "Ja",
        "VirginIslands": "Jungfruöarna",
        "EditCustomerSettings": "Redigera kundinställningar",
        "Continue": "Fortsätt",
        "Nebraska": "Nebraska",
        "NewHampshire": "New Hampshire",
        "DatabaseoSearch": "Databas att söka i",
        "Alaska": "Alaska",
        "PuertoRico": "Puerto Rico",
        "Grey": "Grå",
        "Erroroutput": "Utmatningsfel",
        "RepairCode": "Reparationskod",
        "ZipCode": "Postnummer",
        "yes": "Ja",
        "depotDetails": "Depåuppgifter",
        "stars": "S.T.A.R.S.",
        "Extension": "Anknytning",
        "EquipPartAssetTag": "Utrustningens eller artikelns resurstagg",
        "TestDepotDefined": "Testdepå-definierade data",
        "DefectivePartAsseTag": "Resurstagg för defekt artikel",
        "dateformat": "mm\/dd\/åååå",
        "EndUserViewONLY": "Skrivskyddat för slutanvändare",
        "Zip": "Postadress",
        "PONumber": "PO-nummer",
        "LineRANumber": "Rad\/R.A.-nummer",
        "ApprovalStatus": "Attesteringsstatus",
        "Utah": "Utah",
        "LabelRequest": "Etikettbegäran",
        "ShipTAddress": "Leveransadress",
        "Arizona": "Arizona",
        "Notauthorizedtmakerepairs": "Inte behörig att utföra reparationer utan PO tillhandahålls (av TPS)",
        "forKittedItemsOnly": "endast för utrustade artiklar",
        "PrintFriendly": "Anpassad för utskrift",
        "NorthDakota": "North Dakota",
        "ProblemsExistData": "Det förekommer problem med uppgifterna",
        "USTerritories": "USA-territorier",
        "recordoneoftwo": "registrera en av två",
        "Next": "Nästa",
        "Connecticut": "Connecticut",
        "Country": "Land",
        "OutboundPartModel": "Utgående artikels modell",
        "DiagnosticCode": "Diagnostisk kod",
        "Contract": "Kontrakt",
        "FieldAttributes": "Fältattribut",
        "OutgoingAssetTag": "Utgående resurstagg",
        "InsightPMComments ": "Insight-PM:s kommentarer ",
        "YourSeedStockrecorded": "Din seed-lagerinmatning registrerades",
        "Legend": "Förklaring",
        "CurrentDefectiveEquipment": "Dropbox-innehåll för aktuellt defekt utrustnings modell",
        "Ifreshipyes": "Markera ja om upprepad leverans gäller",
        "CustomerComments": "Kundkommentarer",
        "Massachusetts": "Massachusetts",
        "UserDefinedFieldsCustomer": "Användardefinierade fält – kund",
        "EquipmentModel": "Utrustningens modell",
        "CustomerAddresses": "Kundadresser",
        "ExpressExchange": "Express Exchange",
        "DeploymentID": "Distributions-ID",
        "UserEdit": "Redigera användare",
        "IncomingAssetTag": "Inkommande resurstagg",
        "RhodeIsland": "Rhode Island",
        "ExportToExcel": "Exportera till Excel",
        "DefectiveParSerial": "Defekt artikels serienr",
        "Louisiana": "Louisiana",
        "OriginatedBy": "Upprättat av",
        "OutboundTracking2ndBox": "Utgående spårning, andra fältet",
        "ShipToAddress": "Leveransadress",
        "Company": "Företag",
        "FixedUnderWarranty": "Fast under garanti",
        "CurrentUser": "Aktuell användare",
        "ProblemStatement": "Problembeskrivning",
        "Trackingforunitsent": "Spårning av enhet skickad till Symbol",
        "RedFields": "Röda fält",
        "Quotedpricesaregoodfor": "Angivna priser gäller under",
        "AllCompanies": "Alla företag",
        "PartName": "Kundvagnens namn",
        "note2Email": "Ett för den som ska informeras hos Insight och ett den som ska informeras hos kunden.",
        "CustomerSideUserDefinedFieldsEdit": "Redigera kundsidans användardefinierade fält",
        "ModelNumber": "Modellnummer",
        "DeploymentProjectID": "Distributionsprojekt-ID",
        "HardwarePassword": "Maskinvarulösenord",
        "Units": "Enheter",
        "DefectiveEquipPartAssetTag": "Resurstagg för defekt utrustning eller artikel",
        "MarshallIslands": "Marshallöarna",
        "DefectiveEquipPartSerial": "Defekt utrustnings eller artikels serienr",
        "Both": "Båda",
        "arerequiredfields": "är obligatoriska fält",
        "Oregon": "Oregon",
        "Therarenorecords": "Det finns inga poster för",
        "part": "Artikel",
        "PostalCode": "Postnummer",
        "SelectAll": "Markera alla",
        "DepotViewOnly": "Skrivskyddat för depån",
        "YouarotauthorizedviewDeploymenRequest": "Du har inte behörighet att visa denna distributionsbegäran",
        "DeploymentRequestnotRecorded": "Din distributionsbegäran har INTE registrerats.",
        "CustomerEmailResults": "E-postresultat för kund",
        "NewJersey": "New Jersey",
        "Required": "Krävs",
        "para": "Om den begärda artikeln ovan är en del som kan bytas ut av användaren (del), snarare än en komplett enhet, ska du fylla i avsnittet Information om defekta delar nedan.",
        "EvaluationStatus": "Utvärderingsstatus",
        "DecisionDate": "Beslutsdatum",
        "TestCustomerDefinedData": "Testa kunddefinierade uppgifter",
        "OutboundAssetTag": "Utgående resurstagg",
        "AsseTag": "Resurstagg",
        "InsightComments": "Insight-kommentarer",
        "Quantity": "Antal",
        "WaitingFoApproval": "Väntar på godkännande",
        "ShipToDetails": "Leveransinformation",
        "OriginatedDate": "Ursprungligt datum",
        "NotusedinRepair": "Används inte i reparationsinformationssökningar",
        "OutboundShippingTracking": "Utgående leveransspårning"
    }
}