{"labels":{"Your review is required.":"Uw beoordeling is vereist","I do not want to protect my purchase":"Ik wil mijn aankoop niet beschermen","This is a required selection.":"Dit is een verplichte selectie.","View less accessories":"Bekijk minder accessoires","items to cart":"artikelen naar winkelwagen","You have already created a review for this product.":"U heeft al een recensie voor dit product gemaakt.","Example: Robert23":"Voorbeeld: Robert23","View more protection plans":"Bekijk meer beschermingsplannen","No reviews yet. Be the first.":"Nog geen beoordelingen. Wees de eerste","No, I do not recommend this product":"Nee, ik raad dit product niet aan","Insight recommends adding an extended warranty to your purchase and secure the longevity of your product. Listed below are some of the most popular options for the product you're purchasing.":"Insight raadt aan een verlengde garantie toe te voegen aan uw aankoop","Leave a Review":"Laat een beoordeling achter","Example: Great features":"Voorbeeld: geweldige functies","Total price":"Totale prijs","Tech overview":"Technisch overzicht","List price: ":"Catalogusprijs:","characters remaining":"overgebleven karakters","Contact us for availability & pricing":"Neem contact met ons op voor beschikbaarheid en prijzen","Subtotal":"Subtotaal","Mfr #:":"Fabrikant #:"," instantly":"onmiddellijk","Back to top":"Terug naar boven","Please enter a nickname of at least 5 characters":"Voer een bijnaam in van minimaal 5 tekens","Yes - ":"Ja -","Review title is required":"Titel van de recensie is vereist","Shop":"Shop","Review title is required.":"Titel van de recensie is vereist","In stock":"Op voorraad","Reviews":"Recensies","No comparable products available":"Er zijn geen vergelijkbare producten beschikbaar","List price":"Catalogusprijs","My review":"Mijn beoordeling","Your price: ":"Jouw prijs:","Your review":"Jouw beoordeling","Your price:":"Jouw prijs:","Nickname ":"Bijnaam","Cancel":"Annuleren","View similar items":"Bekijk vergelijkbare artikelen","No - ":"Nee -","Tech specifications":"Technische specificaties","Account Center":"Accountcentrum","(Click to rate)":"(Klik om te beoordelen)","Leave a review":"Laat een beoordeling achter","Specifications":"Specificaties","View all protection plans":"Bekijk alle beschermingsplannen","Manufacturer protection":"Bescherming van de fabrikant","Add to cart":"Voeg toe aan winkelwagen","View less specifications":"Bekijk minder specificaties","Instant savings":"Directe besparingen","Advertised price includes":"Geadverteerde prijs is inclusief","Manufacturer Warranties":"Bescherming van de fabrikant","The price displayed will be prorated in the cart based on the remaining agreement period.":"De weergegeven prijs wordt in de winkelwagen naar rato berekend op basis van de resterende looptijd van de overeenkomst.","Enter a nickname you like. For privacy reasons do not use your full name or email address":"Voer een bijnaam in die je leuk vindt. Gebruik om privacyredenen niet uw","Submit":"Indienen","View full product specifications":"Bekijk de volledige productspecificaties","Add":"Toevoegen","Would you recommend this product?":"Zou u dit product aanbevelen?","No reviews yet. Be the first":"Nog geen beoordelingen. Wees de eerste","Product details":"Productdetails","available":"beschikbaar","Total price:":"Totale prijs:","Review title ":"Titel van de recensie","Protect your purchase":"Bescherm uw aankoop","Out of stock":"Geen voorraad meer","Recommended accessories":"Aanbevolen accessoires","instantly":"onmiddellijk","left in stock":"nog op voorraad","I do not recommend this product":"Ik raad dit product niet aan","Current product":"Huidig ​​product","Reported":"Gerapporteerd","Continue to checkout":"Ga verder naar afrekenen","Better together":"Beter samen","Save ":"Opslaan","View full product details":"Bekijk de volledige productdetails","valid until":"geldig tot","View more specifications":"Bekijk meer specificaties","Tech Overview":"Technisch overzicht","Availability":"Beschikbaarheid","Overall rating":"Algemene rating","This item will ship once it's back in stock.":"Dit artikel wordt verzonden zodra het weer op voorraad is.","Your price":"Jouw prijs","View more accessories":"Bekijk meer accessoires","Was this review helpful?":"Was deze beoordeling nuttig?","Back to results":"Terug naar resultaten","Software Agreement:":"Software-Overeenkomsten:","Continue shopping":"Doorgaan met winkelen","View less protection plans":"Bekijk minder beschermingsplannen","No reviews yet.":"Nog geen beoordelingen.","characters over limit":"tekens boven de limiet","Item backordered":"Artikel nabesteld","People who bought this item also bought":"Mensen die dit artikel kochten, kochten ook","Protection plans":"Beschermingsplannen","Insight #:":"Insight #:","* Required field":"* Verplicht veld","Limited stock":"Beperkte voorraad","This is a required selection":"Dit is een verplichte selectie","Please enter a review title of at least 5 characters":"Voer een recensietitel in van minimaal 5 tekens","Yes":"Ja ","Your review is required":"Uw beoordeling is vereist","Add selected to cart":"Voeg geselecteerde toe aan winkelwagen","Yes, I recommend this product":"Ja, ik raad dit product aan","Accessories":"Accessoires","Required":"Vereist","terms & conditions.":"algemene voorwaarden.","I agree to the":"Ik ga akkoord met de","Add protection":"Voeg bescherming toe","Report an issue":"Een probleem melden","I agree to the terms & conditions.":"Ik ga akkoord met de Algemene Voorwaarden","No items selected":"Geen items geselecteerd","of":"van","ends":"loopt af","Select a rating to filter reviews:":"Selecteer een rating om beoordelingen te filteren:","Be the first.":"Wees de eerste.","I recommend this product.":"Ik raad dit product aan.","Home":"thuis","No":"Nee","Added to cart":"Toegevoegd aan winkelwagen","Item will ship when available":"Het artikel wordt verzonden zodra het beschikbaar is","Nickname is required":"Bijnaam is vereist","Quantity":"Hoeveelheid","Only":"Alleen","Overview":"Overzicht","Search by purchase order, order number, reference number, or PO release number":"Zoek op inkooporder, ordernummer, referentienummer of PO-nummer","Mfr #":"Fabrikant #","Compare similar":"Vergelijk gelijkwaardig","item to cart":"artikel naar winkelwagen","Customer reviews":"Klanten-reviews","Please enter a review of at least 10 characters":"Geef een recensie van minimaal 10 tekens op","I agree to the terms & conditions":"Ik ga akkoord met de Algemene Voorwaarden","Current product:":"Huidig ​​product:"}}
